circe/__init__.py
circe/__main__.py
circe/config.py
circe/static/Sortable.js
circe/static/app.css
circe/static/app.js
circe/static/dropzone.js
circe/static/index.html
circe/tasks.py
circe_certic-0.0.48.dist-info/METADATA
circe_certic-0.0.48.dist-info/WHEEL
circe_certic-0.0.48.dist-info/entry_points.txt
circe_certic-0.0.48.dist-info/RECORD
