Metadata-Version: 2.1
Name: circe-certic
Version: 0.0.48
Summary: Circe Server
License: CECILL-B
Author: Mickaël Desfrênes
Author-email: mickael.desfrenes@unicaen.fr
Requires-Python: >=3.9,<4
Classifier: License :: CeCILL-B Free Software License Agreement (CECILL-B)
Classifier: Programming Language :: Python :: 3
Classifier: Programming Language :: Python :: 3.9
Classifier: Programming Language :: Python :: 3.10
Classifier: Programming Language :: Python :: 3.11
Requires-Dist: aiofiles (==23.2.1)
Requires-Dist: argh (==0.29.4)
Requires-Dist: asyncio (==3.4.3)
Requires-Dist: huey (==2.5.0)
Requires-Dist: itsdangerous (==2.1.2)
Requires-Dist: markdown2 (==2.4.10)
Requires-Dist: python-dotenv (==1.0.0)
Requires-Dist: python-json-logger (==2.0.7)
Requires-Dist: requests (==2.31.0)
Requires-Dist: sanic (==23.6.0)
